oasisis/_version.py
oasisis/activity.py
oasisis/data_utils.py
oasisis/error_terms.py
oasisis/estimation.py
oasisis/helper_func.py
oasisis/input_data.py
oasisis/metropolis_hastings.py
oasisis/operators.py
oasisis/results.py
oasisis/runner.py
oasisis/runner_estimation.py
oasisis/runner_multiday.py
oasisis/settings.py
oasisis/simulation.py
oasisis-0.0.3.dist-info/LICENSE
oasisis-0.0.3.dist-info/METADATA
oasisis-0.0.3.dist-info/WHEEL
oasisis-0.0.3.dist-info/top_level.txt
oasisis-0.0.3.dist-info/RECORD
