Metadata-Version: 2.1
Name: oasisis
Version: 0.0.3
Summary: This is a stable version of the OASIS activity-based framework. This repository includes the simulation code, based on the Python API of the CPLEX solver.
Author-email: Janody Pougala <janody.pougala@epfl.ch>
Keywords: python,disdrometer
Classifier: Development Status :: 1 - Planning
Classifier: Intended Audience :: Developers
Classifier: Programming Language :: Python :: 3
Classifier: Operating System :: Unix
Classifier: Operating System :: MacOS :: MacOS X
Classifier: Operating System :: Microsoft :: Windows
Requires-Python: >=3.8
License-File: LICENSE
Requires-Dist: click
Requires-Dist: cplex
Requires-Dist: docplex
Requires-Dist: joblib
Requires-Dist: json5
Requires-Dist: jsonschema
Requires-Dist: matplotlib
Requires-Dist: numpy
Requires-Dist: ortools
Requires-Dist: pandas
Requires-Dist: python-dateutil
Requires-Dist: python-json-logger
Requires-Dist: scipy
Requires-Dist: seaborn
Provides-Extra: dev
